[{
    "id": 2215491,
    "title": "On Mens Cloudeclipse Running Shoes current Price $99.42",
    "refLink": "",
    "imgTxt": "On Mens Cloudeclipse Running Shoes",
    "imgSRC": "https://dks.scene7.com/is/image/GolfGalaxy/23MAZMCLDCLPSWHTSMNS_Alloy_White?qlt=70&wid=200&hei=200",
    "desc": "On recommends buying your usual size as this model fits true to size Double CloudTec Phase\u00ae cushioning collapses in sequence to absorb impact, providing a soft and smooth ride Dope dyed upper uses 90% less water than standard dyeing techniques",
    "price": "$179.99",
    "curPrice": "$99.42",
    "memo": "$81 Off",
    "moreInfo": "<ul><li><strong><a class=\"hit\" data-id=\"794837\" href=\"https://zdcs.link/z62d2k\" target=\"_blank\">Click Here</a></strong> and select 'Color: Alloy/White' and add to cart for $116.97 - 15% off w/unique coupon when you Email Signup = <span class=\"cpriceb\">$99.42</span> (Offered by Publiclands.com)</li></ul>",
    "timeStamp": "08190115",
    "pid": 0
},{
    "id": 1562301,
    "title": "Airrobo 12000Pa 2L Capcity Pet Grooming Vacuum Kit w/5x Tools current Price $39.99",
    "refLink": "",
    "imgTxt": "Airrobo 12000Pa 2L Capcity Pet Grooming Vacuum Kit w/5x Tools",
    "imgSRC": "https://m.media-amazon.com/images/I/71cp1iMcqaL._AC_AA200_.jpg",
    "desc": "With a strong suction power of up to 12000pa, our dog grooming kit with vacuum function can suck up to 99% of pet hair into the dust box as you groom, preventing pet hair from spreading and creating a mess. Say goodbye to hair-covered furniture and hello to a tidy, fur-free home.",
    "price": "$99.99",
    "curPrice": "$39.99",
    "memo": "$60 Off",
    "moreInfo": "<ul><li><strong><a class=\"hit\" data-id=\"767025\" href=\"https://zdcs.link/9Z5MbK\" target=\"_blank\">Click Here</a></strong> and add to cart for $76.99 - $37.00 off w/coupon <strong>MY7QTP39</strong> = <span class=\"cpriceb\">$39.99 + Free Shipping</span> (Offered by Third Party Merchant and Fulfilled by Amazon)</li>\n",
    "timeStamp": "08190115",
    "pid": 1
},{
    "id": 1915491,
    "title": "Skechers Womens Go Walk 7 Springtime Hands Free Slip-ins Sneaker current Price $26.78",
    "refLink": "",
    "imgTxt": "Skechers Womens Go Walk 7 Springtime Hands Free Slip-ins Sneaker",
    "imgSRC": "https://m.media-amazon.com/images/I/61gr7MpkbhL._AC_AA200_.jpg",
    "desc": "Step-in to convenient walking comfort and cushioning wearing Skechers Hands Free Slip-ins: GO WALK 7 - Springtime. Designed with our exclusive Heel Pillow, this sleek style features a stretch knit upper with a Skechers Air-Cooled Memory Foam insole, lightweight ULTRA GO cushioning, and high-rebound Hyper Pillar Technology for added support.",
    "price": "$109.00",
    "curPrice": "$26.78",
    "memo": "75% Off",
    "moreInfo": "<ul><li><strong><a class=\"hit\" data-id=\"794836\" href=\"https://zdcs.link/Q47l7d\" target=\"_blank\">Click Here</a></strong> and add to cart for <span class=\"cpriceb\">$26.78 + Free Shipping w/$35+ Order</span></li>",
    "timeStamp": "08190115",
    "pid": 2
},{
    "id": 2290491,
    "title": "CINCOM Leg Massager with Heat and Compression current Price $68.89",
    "refLink": "",
    "imgTxt": "CINCOM Leg Massager with Heat and Compression",
    "imgSRC": "https://m.media-amazon.com/images/I/71uWU8FbFvL._AC_AA200_.jpg",
    "desc": "This leg massager for circulation and pain relief fsa combines soothing heat with air compression therapy, delivering a full-leg massage experience",
    "price": "$169.99",
    "curPrice": "$68.89",
    "memo": "$101 Off",
    "moreInfo": "<ul><li><strong><a class=\"hit\" data-id=\"794367\" href=\"https://zdcs.link/Qr2m5D\" target=\"_blank\">Click Here</a></strong> and add to cart for $129.99 - 47% off w/coupon <strong>4OYD8JX8</strong> (Ends 08/24) = <span class=\"cpriceb\">$68.89 + Free Shipping</span> (Offered by Third Party Merchant and Fulfilled by Amazon)</li>\n",
    "timeStamp": "08190115",
    "pid": 3
},{
    "id": 550491,
    "title": "Cili Compression Heat Kneading Shiatsu Foot Massager current Price $53.99",
    "refLink": "",
    "imgTxt": "Cili Compression Heat Kneading Shiatsu Foot Massager",
    "imgSRC": "https://m.media-amazon.com/images/I/81CLQ4o1TkL._AC_AA200_.jpg",
    "desc": "In addition to the standard sole heating feature, CILI foot massager with heat now includes heating for the instep, providing comprehensive warmth for both the soles and the tops of the feet",
    "price": "$109.99",
    "curPrice": "$53.99",
    "memo": "$56 Off",
    "moreInfo": "<ul><li><strong><a class=\"hit\" data-id=\"794381\" href=\"https://zdcs.link/9gb2YD\" target=\"_blank\">Click Here</a></strong> and add to cart for $89.99 - $36.00 off w/coupon <strong>8KIZCFF5</strong> (Ends 08/18) = <span class=\"cpriceb\">$53.99 + Free Shipping</span> (Offered by Third Party Merchant and Fulfilled by Amazon)</li>\n",
    "timeStamp": "08190115",
    "pid": 4
},{
    "id": 1546251,
    "title": "Bodega Cooler 12 Volt Car Fridge 80-Quarts current Price $369.99",
    "refLink": "",
    "imgTxt": "Bodega Cooler 12 Volt Car Fridge 80-Quarts",
    "imgSRC": "https://target.scene7.com/is/image/Target/GUEST_9fd2a63a-9464-4489-be45-1f94148ab2fd?wid=200&hei=200&qlt=80&fmt=webp",
    "desc": "The RV refrigerator supports manual control or APP control (for Android and ios), allowing you to remotely control the temperature and set the modes via a mobile APP. When your car, RV or truck climbs a hill at a 45-degree tilt angle, the 75l in-car refrigerator remains stable.",
    "price": "$999.99",
    "curPrice": "$369.99",
    "memo": "$630 Off",
    "moreInfo": "<ul><li><strong><a class=\"hit\" data-id=\"714515\" href=\"https://zdcs.link/92xZxW\" target=\"_blank\">Click Here</a></strong> and add to cart for <span class=\"cpriceb\">$369.99 + Free Shipping</span> </li></ul>",
    "timeStamp": "08190115",
    "pid": 5
},{
    "id": 2446491,
    "title": "Wentronic Y02 Hybrid Active Noise Cancelling Headphones current Price $29.99",
    "refLink": "",
    "imgTxt": "Wentronic Y02 Hybrid Active Noise Cancelling Headphones",
    "imgSRC": "https://m.media-amazon.com/images/I/512ULpszMNL._AC_AA200_.jpg",
    "desc": "Immerse yourself in tranquillity!Advanced active noise cancellation technology blocks over 95% of ambient noise,whether it's noise in the underground,or the sound of a car or plane engine,the Y02 headphones minimise",
    "price": "$49.99",
    "curPrice": "$29.99",
    "memo": "",
    "moreInfo": "<ul><li><strong><a class=\"hit\" data-id=\"794518\" href=\"https://zdcs.link/QWYLkA\" target=\"_blank\">Click Here</a></strong> and add to cart for $49.99 - $20.00 off w/coupon <strong>6W9LV9CM</strong> = <span class=\"cpriceb\">$29.99 + Free Shipping</span> (Offered by Third Party Merchant and Fulfilled by Amazon)</li>\n",
    "timeStamp": "08190115",
    "pid": 6
},{
    "id": 1315491,
    "title": "Michael Kors Marilyn Medium Satchel current Price $107.80",
    "refLink": "",
    "imgTxt": "Michael Kors Marilyn Medium Satchel",
    "imgSRC": "https://m.media-amazon.com/images/I/91cR3bdQy8L._AC_AA200_.jpg",
    "desc": "A compact companion with enough room for everything, our structured Marilyn satchel is the epitome of polished ease. It features the brand\u2019s initials and opens to a lined interior with dedicated pockets for your phone, wallet and other small items. Attach the smooth leather strap to wear it crossbody.",
    "price": "$298.00",
    "curPrice": "$107.80",
    "memo": "$190 Off",
    "moreInfo": "<ul><li><strong><a class=\"hit\" data-id=\"794834\" href=\"https://zdcs.link/9wR6Rx\" target=\"_blank\">Click Here</a></strong> and add to cart for <span class=\"cpriceb\">$107.80 + Free Shipping w/$35+ Order</span></li>",
    "timeStamp": "08190115",
    "pid": 7
},{
    "id": 1015491,
    "title": "ANBERNIC RG 406H Retro Game Console current Price $114.65",
    "refLink": "",
    "imgTxt": "ANBERNIC RG 406H Retro Game Console",
    "imgSRC": "https://ae-pic-a1.aliexpress-media.com/kf/S6c641459711a41d6a9e0d66a73cd0d8cm.jpg_200x200q75.jpg_.avif",
    "desc": "5500mAh Battery & Fast Charging:Play for longer with the 5500mAh battery, ensuring 7 hours of gaming, and quickly recharge in just 3 hours via USB Type-C.",
    "price": "$239.99",
    "curPrice": "$114.65",
    "memo": "$125 Off",
    "moreInfo": "<ul><li><strong><a class=\"hit\" data-id=\"794833\" href=\"https://zdcs.link/z7OBO8\" target=\"_blank\">Click Here</a></strong> and add to cart for $134.65 - $20.00 off w/coupon <strong>AEUS20</strong> = <span class=\"cpriceb\">$114.65 + Free Shipping</span></li></ul>",
    "timeStamp": "08190115",
    "pid": 8
},{
    "id": 2032191,
    "title": "Dbhal 15000Pa 6000mAh Cordless Handheld Vacuum current Price $14.99",
    "refLink": "",
    "imgTxt": "Dbhal 15000Pa 6000mAh Cordless Handheld Vacuum",
    "imgSRC": "https://m.media-amazon.com/images/I/71wrgdg6+kL._AC_AA200_.jpg",
    "desc": "This handheld vacuum cleaner is equipped with a powerful high-speed motor that delivers 15,000 PA of superb suction as well as a rated speed of 49,000 rpm, allowing you to experience the professional-grade cleaning power at your fingertips.",
    "price": "$49.99",
    "curPrice": "$14.99",
    "memo": "70% Off",
    "moreInfo": "<ul><li><strong><a class=\"hit\" data-id=\"793776\" href=\"https://zdcs.link/QGgJbE\" target=\"_blank\">Click Here</a></strong> and add to cart for $45.99 - $31 Off w/Coupon <strong>ZIN7N9ZX</strong> (Ends 08/24) = <span class=\"cpriceb\">$14.99 + Free Shipping</span> (Offered by Third party merchant and fulfilled by Amazon)</li>\n",
    "timeStamp": "08190115",
    "pid": 9
},{
    "id": 951561,
    "title": "Gotega External DVD Drive, USB 3.0 current Price $9.09",
    "refLink": "",
    "imgTxt": "Gotega External DVD Drive, USB 3.0",
    "imgSRC": "https://m.media-amazon.com/images/I/71h7eXNIVPL._AC_AA200_.jpg",
    "desc": "This external dvd cd drive is compatible with Windows 98 / SE / ME / XP / Vista / Windows /10/8/7, Mac OS (8.6 to 10.14). And perfect for PC, Laptop, Comprehensive Computer, Internal PC hard disk reader. NOT COMPATIBLE with chromebook, blue-ray disks, cars, mobile phones, iPhones, iPads, Tablet, projectors, or TVs.",
    "price": "$21.98",
    "curPrice": "$9.09",
    "memo": "",
    "moreInfo": "<ul><li><strong><a class=\"hit\" data-id=\"781713\" href=\"https://zdcs.link/9yD3v0\" target=\"_blank\">Click Here</a></strong> and add to cart for $13.99 - $4.90 off w/coupon <strong>RMQQLFI2</strong> = <span class=\"cpriceb\">$9.09 + Free Shipping w/$35+ order</span> (Offered by Third Party Merchant and Fulfilled by Amazon)</li>\n",
    "timeStamp": "08190115",
    "pid": 10
},{
    "id": 1726101,
    "title": "Lisen 34.6-in Long Arm Gooseneck 4-12.9-in Tablets Holder Mount current Price $14.24",
    "refLink": "",
    "imgTxt": "Lisen 34.6-in Long Arm Gooseneck 4-12.9-in Tablets Holder Mount",
    "imgSRC": "https://m.media-amazon.com/images/I/71NobuJlq3L._AC_AA200_.jpg",
    "desc": "34.6 inches Long Arm Gooseneck Nintendo Switch Stand Upgraded aviation alloy holder and pro stable: the ipad holder for bed is made of German imported carbon steel and has been carefully polished 10,000+ times.",
    "price": "$29.99",
    "curPrice": "$14.24",
    "memo": "",
    "moreInfo": "<ul><li><strong><a class=\"hit\" data-id=\"763575\" href=\"https://zdcs.link/aM6qlm\" target=\"_blank\">Click Here</a></strong> and add to cart for $28.49 - 50% off (When you clip the coupon on the product page) = <span class=\"cpriceb\">$14.24 + Free Shipping</span> (Offered by Third party merchant and fulfilled by Amazon)</li>\n",
    "timeStamp": "08190115",
    "pid": 11
},{
    "id": 1033071,
    "title": "Star Wars Outlaws PlayStation 5 current Price $9.99",
    "refLink": "",
    "imgTxt": "Star Wars Outlaws PlayStation 5",
    "imgSRC": "https://m.media-amazon.com/images/I/81291v7LnWL._AC_AA200_.jpg",
    "desc": "Experience the first-ever open-world Star Wars game and explore distinct locations across the galaxy, both iconic and new. Risk it all as scoundrel Kay Vess, seeking freedom and the means to start a new life. Fight, steal, and outwit your way through the galaxy\u2019s crime syndicates",
    "price": "$39.99",
    "curPrice": "$9.99",
    "memo": "75% Off",
    "moreInfo": "<ul><li><strong><a class=\"hit\" data-id=\"753443\" href=\"https://zdcs.link/QGg3gE\" target=\"_blank\">Click Here</a></strong> and add to cart for <span class=\"cpriceb\">$9.99 + Free in store pickup</span> </li></ul>",
    "timeStamp": "08190115",
    "pid": 12
},{
    "id": 715491,
    "title": "CAROTE 19-Piece Tri-Ply Stainless Steel Cookware Set current Price $59.99",
    "refLink": "",
    "imgTxt": "CAROTE 19-Piece Tri-Ply Stainless Steel Cookware Set",
    "imgSRC": "https://m.media-amazon.com/images/I/71kPoPcEKEL._AC_AA200_.jpg",
    "desc": "Space-Saving Stackable Design: Detachable handles enable easy storage, saving up to 70% cabinet space \u2014 nested like a compact stockpot. Ideal for small kitchens, RVs & organized storage. Outer ceramic layer resists stains and is dishwasher friendly. Rivet-free interior prevents food trapping for hassle-free maintenance.",
    "price": "$199.99",
    "curPrice": "$59.99",
    "memo": "70% Off",
    "moreInfo": "<ul><li><strong><a class=\"hit\" data-id=\"794832\" href=\"https://zdcs.link/z3GNG2\" target=\"_blank\">Click Here</a></strong> and add to cart for $99.99 - 40% Off w/Coupon <strong>6O8WHO96</strong> = <span class=\"cpriceb\">$59.99 + Free Shipping</span> (Offered by Third Party Merchant and Fulfilled by Amazon) </li>",
    "timeStamp": "08190115",
    "pid": 13
},{
    "id": 162348,
    "title": "Adidas Steel Straw Metal Bottle 20oz current Price $12.60",
    "refLink": "",
    "imgTxt": "Adidas Steel Straw Metal Bottle 20oz",
    "imgSRC": "https://assets.adidas.com/images/h_200,f_auto,q_auto,fl_lossy,c_fill,g_auto/33b51c4296914d12a602ab8b0118fd23_9366/Steel_Straw_Metal_Bottle_600_ML_Grey_EW4918_01_standard.jpg",
    "desc": "This bottle likes a challenge. Whether you want access to cold water all day long on your hike to the summit or just need to keep coffee hot during your kid's hockey tournament this Saturday, the double-walled insulation does the trick.",
    "price": "$30.00",
    "curPrice": "$12.60",
    "memo": "",
    "moreInfo": "<ul><li><strong><a class=\"hit\" data-id=\"611450\" href=\"https://zdcs.link/aNJO7E\" target=\"_blank\">Click Here</a></strong> and add to cart for $18.00 - 30% off w/coupon <strong>SUMMER</strong> (Ends 08/21) = <span class=\"cpriceb\">$12.60</span></li>\n",
    "timeStamp": "08190115",
    "pid": 14
},{
    "id": 530361,
    "title": "Mentech HY300PRO Mini Projector w/WiFi and Bluetooth current Price $32.99",
    "refLink": "",
    "imgTxt": "Mentech HY300PRO Mini Projector w/WiFi and Bluetooth",
    "imgSRC": "https://m.media-amazon.com/images/I/811eNZ5EFpL._AC_AA200_.jpg",
    "desc": "Experience the ultimate flexibility with the Mentech mini Projector\u2019s 180\u00b0rotatable design, enabling projection onto any surface, including ceilings, without the need for fixed installation. Enjoy a massive 150'' screen, turning any space into an immersive theater. With a long-lasting light source of up to 50,000 hours, it\u2019s perfect for movies, gaming, and sports.",
    "price": "$69.99",
    "curPrice": "$32.99",
    "memo": "$37 Off",
    "moreInfo": "<ul><li><strong><a class=\"hit\" data-id=\"787671\" href=\"https://zdcs.link/aBgLlJ\" target=\"_blank\">Click Here</a></strong> and add to cart for $59.99 - $27.00 Off w/Coupon <strong>KY574XHV</strong> = <span class=\"cpriceb\">$32.99 + Free Shipping</span> (Offered by Third Party Merchant and Fulfilled by Amazon)</li>\n",
    "timeStamp": "08190115",
    "pid": 15
},{
    "id": 1669491,
    "title": "Adidas Mens Astrastar Sneakers current Price $37.10",
    "refLink": "",
    "imgTxt": "Adidas Mens Astrastar Sneakers",
    "imgSRC": "https://assets.adidas.com/images/h_200,f_auto,q_auto,fl_lossy,c_fill,g_auto/4cc0934b84ff4b468cbeb754313ac697_9366/Astrastar_Shoes_Black_JR5563_01_00_standard.jpg",
    "desc": "Inspired by the top technologies of the adidas running line, the Astrastar is built for the sports lifestyle. The Cloudfoam midsole delivers lightweight cushioning for a smooth ride, no matter where you're headed. Whether you're hitting the gym or the streets, these versatile trainers keep you comfortable and stylish.",
    "price": "$75.",
    "curPrice": "$37.10",
    "memo": "",
    "moreInfo": "<ul><li><strong><a class=\"hit\" data-id=\"794655\" href=\"https://zdcs.link/QGgLRW\" target=\"_blank\">Click Here</a></strong> and add to cart for $53.00 - 30% off w/coupon <strong>SUMMER</strong> (Ends 08/21) = <span class=\"cpriceb\">$37.10</span></li>\n",
    "timeStamp": "08190115",
    "pid": 16
},{
    "id": 2785491,
    "title": "Mahomico Big & Tall Ergonomic Office Chair current Price $95.99",
    "refLink": "",
    "imgTxt": "Mahomico Big & Tall Ergonomic Office Chair",
    "imgSRC": "https://m.media-amazon.com/images/I/61SneyiwtML._AC_AA200_.jpg",
    "desc": "Thick padding complements the breathable mesh back, offering full-body support while effectively distributing pressure. We proudly recommend the ATLAS 750 \u2014 the most comfortable office chair for your workspace. Featuring an oversized U-shaped seat cushion, it creates a personalized comfort zone.",
    "price": "$199.99",
    "curPrice": "$95.99",
    "memo": "$104 Off",
    "moreInfo": "<ul><li><strong><a class=\"hit\" data-id=\"794829\" href=\"https://zdcs.link/QP868y\" target=\"_blank\">Click Here</a></strong> and add to cart for $159.99 - 50% Off w/Coupon <strong>MAHOMICO</strong> = <span class=\"cpriceb\">$95.99 + Free Shipping</span> (Offered by Third Party Merchant and Fulfilled by Amazon)</li>",
    "timeStamp": "08190115",
    "pid": 17
},{
    "id": 1096491,
    "title": "FOCO NBA Team Logo Sport Outdoor Sun Boonie Hat current Price $5.91",
    "refLink": "",
    "imgTxt": "FOCO NBA Team Logo Sport Outdoor Sun Boonie Hat",
    "imgSRC": "https://m.media-amazon.com/images/I/619iGLl7brL._AC_AA200_.jpg",
    "desc": "All-over, team-colored design. Embroidered team logo display. Team-colored, tropical design with repeat team logo display on panel under brim Adjustable black lace chin string for a comfortable wear Top vent eyelets for optimal air flow and comfort.",
    "price": "$10.14",
    "curPrice": "$5.91",
    "memo": "",
    "moreInfo": "<ul><li><strong><a class=\"hit\" data-id=\"794563\" href=\"https://zdcs.link/9gb2nq\" target=\"_blank\">Click Here</a></strong> and add to cart for <span class=\"cpriceb\">$5.91 + Free Shipping w/$35+ Order</span></li>",
    "timeStamp": "08190115",
    "pid": 18
},{
    "id": 2485491,
    "title": "WANFUN 15-in-1 Foldable Portable Pilates Board Reformer current Price $64.50",
    "refLink": "",
    "imgTxt": "WANFUN 15-in-1 Foldable Portable Pilates Board Reformer",
    "imgSRC": "https://m.media-amazon.com/images/I/61N77jRBtnL._AC_AA200_.jpg",
    "desc": "Pilates Reformer Board integrates 15 versatile functions, including core trainer, resistance band, push-up handles, balance board, ab roller, and plank support. It effectively shapes abs, builds muscle, burns fat, improves flexibility, and aids rehabilitation, making it perfect for everyone from beginners to advanced fitness enthusiasts.",
    "price": "$179.00",
    "curPrice": "$64.50",
    "memo": "$115 Off",
    "moreInfo": "<ul><li><strong><a class=\"hit\" data-id=\"794828\" href=\"https://zdcs.link/985n5v\" target=\"_blank\">Click Here</a></strong> and add to cart for $129.00 - 50% Off w/Coupon <strong>QFCO3SC3</strong> = <span class=\"cpriceb\">$64.50 + Free Shipping</span> (Offered by Third Party Merchant and Fulfilled by Amazon) </li>\n",
    "timeStamp": "08190115",
    "pid": 19
},{
    "id": 1252491,
    "title": "Adidas Originals Roller 3.0 3-Pack Crew Socks current Price $7.70",
    "refLink": "",
    "imgTxt": "Adidas Originals Roller 3.0 3-Pack Crew Socks",
    "imgSRC": "https://assets.adidas.com/images/h_200,f_auto,q_auto,fl_lossy,c_fill,g_auto/a4295cdd08fa4062a08c98b91a1b3eb7_9366/Originals_Roller_3.0_3-Pack_Crew_Socks_White_IR1075_03_standard.jpg",
    "desc": "Want 3-Stripes or only one? You've got options when you wear these adidas crew socks. Comfortable and simple, these socks come three pairs to a pack.",
    "price": "$18.00",
    "curPrice": "$7.70",
    "memo": "",
    "moreInfo": "<ul><li><strong><a class=\"hit\" data-id=\"794714\" href=\"https://zdcs.link/985np1\" target=\"_blank\">Click Here</a></strong> and add to cart for $11.00 - 30% off w/coupon <strong>SUMMER</strong> (Ends 08/21) = <span class=\"cpriceb\">$7.70</span></li>\n",
    "timeStamp": "08190115",
    "pid": 20
},{
    "id": 2604501,
    "title": "DOVE MEN + CARE Body Wash Sandalwood + Cardamom Oil 26oz current Price $4.70",
    "refLink": "",
    "imgTxt": "DOVE MEN + CARE Body Wash Sandalwood + Cardamom Oil 26oz",
    "imgSRC": "https://m.media-amazon.com/images/I/71Fo1LdrIJL._AC_AA200_.jpg",
    "desc": "Refresh your shower with Sandalwood + Cardamom Oil Plant Powered Body Wash & make it a part of your daily grooming routine, for smoother and healthier skin.",
    "price": "$10.97",
    "curPrice": "$4.70",
    "memo": "",
    "moreInfo": "<ul>\n<li><strong><a class=\"hit\" data-id=\"761868\" href=\"https://zdcs.link/QGGD88\" target=\"_blank\">Click Here</a></strong> and add to cart for $10.97 - 10% off w/Subscribe &amp; Save - $2.98 off (When you clip the coupon on the product page) - 20% off (When you <a class=\"hit\" data-id=\"761868\" href=\"https://zdcs.link/aoGoZA\" target=\"_blank\">Click Here</a> to activate 20% Off Coupon) = <span class=\"cpriceb\">$4.70 + Free Shipping w/$35+ Order</span></li>\n",
    "timeStamp": "08190115",
    "pid": 21
},{
    "id": 1041558,
    "title": "Frost King ACF19 Foam Coil Cleaner 19oz current Price $4.54",
    "refLink": "",
    "imgTxt": "Frost King ACF19 Foam Coil Cleaner 19oz",
    "imgSRC": "https://m.media-amazon.com/images/I/81zUHr1aM0L._AC_AA200_.jpg",
    "desc": "Heavy-duty foam dissolves stains, removes grease & oil, and loosens dirt Cleans coils, fan blades, and reusable air filters Neutralizes odors from standing water in drain pans.",
    "price": "$16.10",
    "curPrice": "$4.54",
    "memo": "72% Off",
    "moreInfo": "<ul><li><strong><a class=\"hit\" data-id=\"681743\" href=\"https://zdcs.link/VmwBO\" target=\"_blank\">Click Here</a></strong> and add to cart for <span class=\"cpriceb\">$4.54 + Free Shipping w/$35+ Order</span> </li>",
    "timeStamp": "08190115",
    "pid": 22
},{
    "id": 1585491,
    "title": "12-Piece ZHFUYS Metal Mini Cars Toy current Price $7.99",
    "refLink": "",
    "imgTxt": "12-Piece ZHFUYS Metal Mini Cars Toy",
    "imgSRC": "https://m.media-amazon.com/images/I/81EohQ2+oWL._AC_AA200_.jpg",
    "desc": "12 construction vehicles in 12 bold colors stimulate visual development and enhance color recognition, making them perfect for sandbox play and sensory exploration. Each vehicle features moving parts like rotating wheels and adjustable scoops, encouraging hands-on learning in sand or indoor play while developing fine motor skills and mechanical curiosity.",
    "price": "$19.99",
    "curPrice": "$7.99",
    "memo": "",
    "moreInfo": "<ul><li><strong><a class=\"hit\" data-id=\"794825\" href=\"https://zdcs.link/QVXWXx\" target=\"_blank\">Click Here</a></strong> and add to cart for $15.99 - 50% Off w/Coupon <strong>BLK438IV</strong> = <span class=\"cpriceb\">$7.99 + Free Shipping w/$35+ order</span> (Offered by Third Party Merchant and Fulfilled by Amazon) </li>",
    "timeStamp": "08190115",
    "pid": 23
},{
    "id": 2499591,
    "title": "Trimui Smart Pro Consoles 4.96-in IPS Handheld Game Players current Price $41.39",
    "refLink": "",
    "imgTxt": "Trimui Smart Pro Consoles 4.96-in IPS Handheld Game Players",
    "imgSRC": "https://ae-pic-a1.aliexpress-media.com/kf/S80c6c0333f0f4639913cfa93fea71369O.jpg_200x200q75.jpg_.avif",
    "desc": "Ampown Trimui UI System Smart Pro 4.96'' IPS Handheld Game Players Linux System Video Game Console 5000mAh 9000+ Retro Games N64",
    "price": "$122.36",
    "curPrice": "$41.39",
    "memo": "$81 Off",
    "moreInfo": "<ul><li><strong><a class=\"hit\" data-id=\"791338\" href=\"https://zdcs.link/av454W\" target=\"_blank\">Click Here</a></strong> and add to cart for $51.39 - $10.00 off w/coupon <strong>AEUS10</strong> = <span class=\"cpriceb\">$41.39 + Free Shipping</span></li></ul>",
    "timeStamp": "08190115",
    "pid": 24
},{
    "id": 1721508,
    "title": "8-Pack Swcandy Aromatherapy Shower Steamers current Price $3.99",
    "refLink": "",
    "imgTxt": "8-Pack Swcandy Aromatherapy Shower Steamers",
    "imgSRC": "https://m.media-amazon.com/images/I/818vE9u0GHL._AA200_.jpg",
    "desc": "SWCANDY shower bombs have upgraded the current shower steamers formula. The latest 2025 verition delivers extra strength of a concentrated serum for a stronger aromatherapy fragrance and long-lasting results.",
    "price": "$15.99",
    "curPrice": "$3.99",
    "memo": "75% Off",
    "moreInfo": "<ul>\n<li><strong><a class=\"hit\" data-id=\"638375\" href=\"https://zdcs.link/QGgL3x\" target=\"_blank\">Click Here</a></strong> and add to cart for $7.98 - 50% off w/coupon <strong>GALNGQMJ</strong> = <span class=\"cpriceb\">$3.99 + Free Shipping w/$35+ Order</span> (Offered by Third Party Merchant and Fulfilled by Amazon)</li>\n",
    "timeStamp": "08190115",
    "pid": 25
},{
    "id": 1285491,
    "title": "6-Pack Hydroburst Reusable Water Balloons current Price $7.29",
    "refLink": "",
    "imgTxt": "6-Pack Hydroburst Reusable Water Balloons",
    "imgSRC": "https://m.media-amazon.com/images/I/71xjcCbd+uL._AC_AA200_.jpg",
    "desc": "These reusable water balloons take the stress out of filling and tying water balloons for instant excitement. Use them as pool toys or load 'em up for your favorite beach games.  Each balloon uses a self-sealing technology when filled. This helps minimize cleanup and reduces the need for extra balloons during play.",
    "price": "$12.99",
    "curPrice": "$7.29",
    "memo": "",
    "moreInfo": "<ul><li><strong><a class=\"hit\" data-id=\"794824\" href=\"https://zdcs.link/9gbnbe\" target=\"_blank\">Click Here</a></strong> and add to cart for <span class=\"cpriceb\">$7.29 + Free Shipping w/$35+ Order</span></li>",
    "timeStamp": "08190115",
    "pid": 26
},{
    "id": 2483901,
    "title": "5-Pk Anker USB C to USB C Cable Type C 100W 6ft Fast Charging current Price $13.99",
    "refLink": "",
    "imgTxt": "5-Pk Anker USB C to USB C Cable Type C 100W 6ft Fast Charging",
    "imgSRC": "https://m.media-amazon.com/images/I/919E8b1016L._AC_AA200_.jpg",
    "desc": "The Anker Advantage: Join the 80 million+ powered by our leading technology. Rapid Charging: Supports high-speed charging up to 100W when used with a compatible charger.",
    "price": "$23.99",
    "curPrice": "$13.99",
    "memo": "",
    "moreInfo": "<ul><li><strong><a class=\"hit\" data-id=\"769728\" href=\"https://zdcs.link/akKeKX\" target=\"_blank\">Click Here</a></strong> and add to cart for <span class=\"cpriceb\">$13.99 + Free Shipping w/$35+ Order</span> (Offered by Third party merchant and fulfilled by Amazon)</li>\n",
    "timeStamp": "08190115",
    "pid": 27
},{
    "id": 2214171,
    "title": "5-Pack 3M Claw Drywall Picture Hanger Set current Price $5.99",
    "refLink": "",
    "imgTxt": "5-Pack 3M Claw Drywall Picture Hanger Set",
    "imgSRC": "https://m.media-amazon.com/images/I/71FL2Q0ACVL._AC_AA200_.jpg",
    "desc": "Pack of five 15 lb. 3M CLAW(TM) Drywall Picture Hangers; each picture hanger made of hardened steel, proven to hold 15 lbs., so you can hang decor, such as pictures, mirrors and other heavy objects; Also includes five spot markers. Engineered hardened steel claws lock securely into drywall anywhere, so you can hang large mirrors and art easily.",
    "price": "$11.99",
    "curPrice": "$5.99",
    "memo": "",
    "moreInfo": "<ul><li><strong><a class=\"hit\" data-id=\"750837\" href=\"https://zdcs.link/aDVorw\" target=\"_blank\">Click Here</a></strong> and add to cart for <span class=\"cpriceb\">$5.99 + Free Shipping w/$35+ Order</span></li>",
    "timeStamp": "08190115",
    "pid": 28
},{
    "id": 710331,
    "title": "Skechers Mens Cavell Hensley Memory Foam Court Sneaker current Price $29.99",
    "refLink": "",
    "imgTxt": "Skechers Mens Cavell Hensley Memory Foam Court Sneaker",
    "imgSRC": "https://i5.walmartimages.com/seo/Skechers-Men-s-Cavell-Hensley-Memory-Foam-Court-Sneaker_669ef062-3311-4134-b5b0-020cab25b4de.f0c8c75e8beb901f9d12c96d187a758c.jpeg?odnHeight=200&odnWidth=200&odnBg=FFFFFF",
    "desc": "Skechers; Low profile court style sneaker; 6 Eyelet Lace to Toe Design; Synthetic Leather Upper; Air-Cooled Memory Foam insole; Skechers Classic Medium Fit. Low profile court style sneaker.",
    "price": "$49.99",
    "curPrice": "$29.99",
    "memo": "$20 Off",
    "moreInfo": "<ul><li><strong><a class=\"hit\" data-id=\"777632\" href=\"https://zdcs.link/zEgLLP\" target=\"_blank\">Click Here</a></strong> and add to cart for <span class=\"cpriceb\">$29.99 + Free Shipping w/$35+ order</span> </li></ul>",
    "timeStamp": "08190115",
    "pid": 29
},{
    "id": 1771491,
    "title": "LE PAON Sewing Kit with Case Portable Sewing Supplies current Price $3.99",
    "refLink": "",
    "imgTxt": "LE PAON Sewing Kit with Case Portable Sewing Supplies",
    "imgSRC": "https://m.media-amazon.com/images/I/81cbuc-19xL._AC_AA200_.jpg",
    "desc": "Sewing KIT, DIY Sewing Supplies with Sewing Accessories, Portable Mini Sewing Kit contains all 18 spools thread ( 18 color\uff0c100 meters/ spool) and the necessary tools that are required for performing basic repairs with everything you need for hand sewing jobs and crafts.",
    "price": "$7.99",
    "curPrice": "$3.99",
    "memo": "",
    "moreInfo": "<ul><li><strong><a class=\"hit\" data-id=\"794095\" href=\"https://zdcs.link/QL8joX\" target=\"_blank\">Click Here</a></strong> and add to cart for <span class=\"cpriceb\">$3.99 + Free Shipping w/$35+ Order</span> (Offered by Third Party Merchant and Fulfilled by Amazon)</li>\n",
    "timeStamp": "08190115",
    "pid": 30
},{
    "id": 769491,
    "title": "Brahma Mens Ripstop Shirt with Short Sleeves current Price $8.13",
    "refLink": "",
    "imgTxt": "Brahma Mens Ripstop Shirt with Short Sleeves",
    "imgSRC": "https://i5.walmartimages.com/asr/7255f8af-9189-46d7-bfc0-565164ac760f.06c8507fc2e3a10cec73d9143347ecbf.jpeg?odnHeight=200&odnWidth=200&odnBg=FFFFFF",
    "desc": "Relaxed Fit: Designed for comfort, this shirt offers a relaxed fit ideal for all-day wear. Durable Material: Made from 97% cotton and 3% spandex, providing a blend of comfort and flexibility. Functional Design: Features two button flap chest pockets and a pencil slot for convenient storage of small items.",
    "price": "$18.98",
    "curPrice": "$8.13",
    "memo": "",
    "moreInfo": "<ul><li><strong><a class=\"hit\" data-id=\"794652\" href=\"https://zdcs.link/QKgLNE\" target=\"_blank\">Click Here</a></strong> and add to cart for <span class=\"cpriceb\">$8.13 + Free Shipping w/$35+ order</span> </li></ul>",
    "timeStamp": "08190115",
    "pid": 31
},{
    "id": 2847858,
    "title": "3-Count Febreze Car Air Freshener Odor-Fighting Vent Clip current Price $4.34",
    "refLink": "",
    "imgTxt": "3-Count Febreze Car Air Freshener Odor-Fighting Vent Clip",
    "imgSRC": "https://m.media-amazon.com/images/I/61hWuKrcUgL._AC_AA200_.jpg",
    "desc": "Fresh, fruity, or floral, this pack has a CAR Vent Clip for every scent-style\u200b Drive odors out with a car air freshener that has a distinct air of sophistication Easy to install: Click to activate, clip into vent, adjust scent level, and sniff on.",
    "price": "$7.34",
    "curPrice": "$4.34",
    "memo": "",
    "moreInfo": "<ul><li><strong><a class=\"hit\" data-id=\"682949\" href=\"https://zdcs.link/9YWbbm\" target=\"_blank\">Click Here</a></strong> and add to cart for $7.34 - $3 Off (When you clip the coupon on the product page) = <span class=\"cpriceb\">$4.34 + Free Shipping w/$35+ Order</span></li>\n",
    "timeStamp": "08190115",
    "pid": 32
},{
    "id": 169491,
    "title": "WRYBV 16-inch Retractable Ceiling Fans w/Lights and Remote current Price $7.99",
    "refLink": "",
    "imgTxt": "WRYBV 16-inch Retractable Ceiling Fans w/Lights and Remote",
    "imgSRC": "https://m.media-amazon.com/images/I/5193ArK14FL._AC_AA200_.jpg",
    "desc": "The fan blades are crafted from a warm brown-toned PC material with a translucent effect, giving them a unique and almost sculptural quality. When the fan is turned on, these blades extend outward",
    "price": "",
    "curPrice": "$7.99",
    "memo": "",
    "moreInfo": "<ul><li><strong><a class=\"hit\" data-id=\"794650\" href=\"https://zdcs.link/znx0G4\" target=\"_blank\">Click Here</a></strong> and add to cart for <span class=\"cpriceb\">$7.99 + Free Shipping w/$35+ order</span> (Offered by Third Party Merchant and Fulfilled by Amazon)\r\n\r\n\r\n",
    "timeStamp": "08190115",
    "pid": 33
}]